aye/.gitignore
aye/__init__.py
aye/__main__.py
aye/__main_chat__.py
aye/controller/__init__.py
aye/controller/command_handlers.py
aye/controller/commands.py
aye/controller/llm_handler.py
aye/controller/llm_invoker.py
aye/controller/plugin_manager.py
aye/controller/repl.py
aye/controller/tutorial.py
aye/controller/util.py
aye/model/__init__.py
aye/model/api.py
aye/model/ast_chunker.py
aye/model/auth.py
aye/model/config.py
aye/model/download_plugins.py
aye/model/file_processor.py
aye/model/ignore_patterns.py
aye/model/json_extractor.py
aye/model/models.py
aye/model/offline_llm_manager.py
aye/model/onnx_manager.py
aye/model/source_collector.py
aye/model/telemetry.py
aye/model/vector_db.py
aye/model/version_checker.py
aye/model/write_validator.py
aye/model/index_manager/__init__.py
aye/model/index_manager/index_manager.py
aye/model/index_manager/index_manager_executor.py
aye/model/index_manager/index_manager_file_ops.py
aye/model/index_manager/index_manager_state.py
aye/model/index_manager/index_manager_utils.py
aye/model/snapshot/__init__.py
aye/model/snapshot/base.py
aye/model/snapshot/file_backend.py
aye/model/snapshot/git_ref_backend.py
aye/plugins/__init__.py
aye/plugins/at_file_completer.py
aye/plugins/auto_detect_mask.py
aye/plugins/completer.py
aye/plugins/local_model.py
aye/plugins/offline_llm.py
aye/plugins/plugin_base.py
aye/plugins/shell_executor.py
aye/plugins/slash_completer.py
aye/presenter/__init__.py
aye/presenter/cli_ui.py
aye/presenter/diff_presenter.py
aye/presenter/repl_ui.py
aye/presenter/streaming_ui.py
aye/presenter/ui_utils.py
ayechat_dev-0.36.9.20260201141756.dist-info/licenses/LICENSE
ayechat_dev-0.36.9.20260201141756.dist-info/METADATA
ayechat_dev-0.36.9.20260201141756.dist-info/WHEEL
ayechat_dev-0.36.9.20260201141756.dist-info/entry_points.txt
ayechat_dev-0.36.9.20260201141756.dist-info/top_level.txt
ayechat_dev-0.36.9.20260201141756.dist-info/RECORD
